<annotation>
	<folder>pedro</folder>
	<filename>20190416_212802.jpg</filename>
	<path>D:\pedro\20190416_212802.jpg</path>
	<source>
		<database>Unknown</database>
	</source>
	<size>
		<width>2560</width>
		<height>1536</height>
		<depth>3</depth>
	</size>
	<segmented>0</segmented>
	<object>
		<name>41-60</name>
		<pose>Unspecified</pose>
		<truncated>1</truncated>
		<difficult>0</difficult>
		<bndbox>
			<xmin>499</xmin>
			<ymin>7</ymin>
			<xmax>2234</xmax>
			<ymax>1536</ymax>
		</bndbox>
	</object>
</annotation>
